paltax/__init__.py
paltax/cosmology_utils.py
paltax/cosmology_utils_test.py
paltax/hierarchical_inference.py
paltax/hierarchical_inference_test.py
paltax/image_simulation.py
paltax/image_simulation_test.py
paltax/input_pipeline.py
paltax/input_pipeline_test.py
paltax/lens_models.py
paltax/lens_models_test.py
paltax/los.py
paltax/los_test.py
paltax/main.py
paltax/models.py
paltax/nfw_functions.py
paltax/nfw_functions_test.py
paltax/power_law.py
paltax/power_law_test.py
paltax/power_spectrum.py
paltax/power_spectrum_test.py
paltax/psf_models.py
paltax/psf_models_test.py
paltax/source_models.py
paltax/source_models_test.py
paltax/subhalos.py
paltax/subhalos_test.py
paltax/train.py
paltax/train_snpe.py
paltax/train_snpe_test.py
paltax/train_test.py
paltax/utils.py
paltax/utils_test.py
paltax/TrainConfigs/train_config_500k.py
paltax/TrainConfigs/train_config_50k.py
paltax/TrainConfigs/train_config_5M.py
paltax/TrainConfigs/train_config_constant.py
paltax/TrainConfigs/train_config_exp_fast.py
paltax/TrainConfigs/train_config_exp_slow.py
paltax/TrainConfigs/train_config_linear.py
paltax/TrainConfigs/train_config_linear_0p001.py
paltax/TrainConfigs/train_config_npe_base.py
paltax/TrainConfigs/train_config_res_18.py
paltax/TrainConfigs/train_config_res_18_small.py
paltax/TrainConfigs/train_config_res_18_very_small.py
paltax/TrainConfigs/train_config_res_34.py
paltax/TrainConfigs/train_config_res_d.py
paltax/TrainConfigs/train_config_snpe_base.py
paltax/TrainConfigs/train_config_snpe_instant_avg.py
paltax/TrainConfigs/train_config_snpe_m_ad.py
paltax/test_files/cosmos_galaxies_testing.npz
paltax-1.0.1.dist-info/LICENSE.txt
paltax-1.0.1.dist-info/METADATA
paltax-1.0.1.dist-info/WHEEL
paltax-1.0.1.dist-info/top_level.txt
paltax-1.0.1.dist-info/RECORD
