Metadata-Version: 2.1
Name: paltax
Version: 1.0.1
Summary: Strong lensing package using jax
Home-page: https://github.com/swagnercarena/paltax
Author: Sebastian Wagner-Carena
Author-email: sebaswagner@outlook.com
License: Apache2.0
License-File: LICENSE.txt
Requires-Dist: chex
Requires-Dist: dm-pix
Requires-Dist: immutabledict
Requires-Dist: jax
Requires-Dist: tensorflow
Requires-Dist: clu
Requires-Dist: flax
Requires-Dist: ml-collections
Requires-Dist: optax
Requires-Dist: numba
